setup.py
ctarn/__init__.py
ctarn.egg-info/PKG-INFO
ctarn.egg-info/SOURCES.txt
ctarn.egg-info/dependency_links.txt
ctarn.egg-info/entry_points.txt
ctarn.egg-info/requires.txt
ctarn.egg-info/top_level.txt
ctarn/cluster/__init__.py
ctarn/cluster/connect.py
ctarn/cluster/dendrogram.py
ctarn/cluster/evaluate.py
ctarn/cluster/prune.py
ctarn/cluster/reductive.py
ctarn/cluster/select.py
ctarn/cluster/smooth.py
ctarn/demo/__init__.py
ctarn/demo/rc.py
ctarn/util/__init__.py
ctarn/util/dataset.py
ctarn/util/visualize.py
test/cluster/__init__.py
test/cluster/test_dendrogram.py
test/util/__init__.py