Metadata-Version: 1.0
Name: ctarn
Version: 1
Summary: Tarn Yeong Ching
Home-page: http://res.ctarn.io
Author: Tarn Yeong Ching
Author-email: i@ctarn.io
License: Public Domain
Platform: UNKNOWN
